uplink_protobuf/__about__.py
uplink_protobuf/__init__.py
uplink_protobuf/converter.py
uplink_protobuf/helpers.py
uplink_protobuf/json_options.py
uplink_protobuf-0.1.0.dist-info/METADATA
uplink_protobuf-0.1.0.dist-info/RECORD
uplink_protobuf-0.1.0.dist-info/WHEEL
uplink_protobuf-0.1.0.dist-info/entry_points.txt
uplink_protobuf-0.1.0.dist-info/top_level.txt
