Metadata-Version: 2.1
Name: uplink-protobuf
Version: 0.1.0
Summary: Protocol Buffers (Protobuf) support for Uplink.
Home-page: https://github.com/prkumar/uplink-protobuf
Author: P. Raj Kumar
Author-email: raj.pritvi.kumar@gmail.com
License: MIT
Keywords: http api rest client retrofit protobuf protocol buffers
Platform: UNKNOWN
Classifier: Development Status :: 4 - Beta
Classifier: Intended Audience :: Developers
Classifier: License :: OSI Approved :: MIT License
Classifier: Programming Language :: Python
Classifier: Programming Language :: Python :: 2
Classifier: Programming Language :: Python :: 2.7
Classifier: Programming Language :: Python :: 3
Classifier: Programming Language :: Python :: 3.3
Classifier: Programming Language :: Python :: 3.4
Classifier: Programming Language :: Python :: 3.5
Classifier: Programming Language :: Python :: 3.6
Classifier: Programming Language :: Python :: Implementation :: CPython
Classifier: Programming Language :: Python :: Implementation :: PyPy
Provides-Extra: tests
